<annotation>
	<folder>图片标注1</folder>
	<filename>004134.jpg</filename>
	<path>D:\桌面\毕设标注\毕设标注1\图片标注1\004134.jpg</path>
	<source>
		<database>Unknown</database>
	</source>
	<size>
		<width>1280</width>
		<height>720</height>
		<depth>3</depth>
	</size>
	<segmented>0</segmented>
	<object>
		<name>jars</name>
		<pose>Unspecified</pose>
		<truncated>0</truncated>
		<difficult>0</difficult>
		<bndbox>
			<xmin>100</xmin>
			<ymin>424</ymin>
			<xmax>219</xmax>
			<ymax>629</ymax>
		</bndbox>
	</object>
	<object>
		<name>glass-rod</name>
		<pose>Unspecified</pose>
		<truncated>0</truncated>
		<difficult>0</difficult>
		<bndbox>
			<xmin>139</xmin>
			<ymin>123</ymin>
			<xmax>170</xmax>
			<ymax>626</ymax>
		</bndbox>
	</object>
	<object>
		<name>dropper</name>
		<pose>Unspecified</pose>
		<truncated>0</truncated>
		<difficult>0</difficult>
		<bndbox>
			<xmin>163</xmin>
			<ymin>371</ymin>
			<xmax>196</xmax>
			<ymax>600</ymax>
		</bndbox>
	</object>
	<object>
		<name>beaker</name>
		<pose>Unspecified</pose>
		<truncated>0</truncated>
		<difficult>0</difficult>
		<bndbox>
			<xmin>227</xmin>
			<ymin>407</ymin>
			<xmax>383</xmax>
			<ymax>628</ymax>
		</bndbox>
	</object>
	<object>
		<name>narrow-necked-bottle</name>
		<pose>Unspecified</pose>
		<truncated>0</truncated>
		<difficult>0</difficult>
		<bndbox>
			<xmin>374</xmin>
			<ymin>388</ymin>
			<xmax>521</xmax>
			<ymax>632</ymax>
		</bndbox>
	</object>
	<object>
		<name>measuring-cylinder</name>
		<pose>Unspecified</pose>
		<truncated>0</truncated>
		<difficult>0</difficult>
		<bndbox>
			<xmin>518</xmin>
			<ymin>243</ymin>
			<xmax>614</xmax>
			<ymax>634</ymax>
		</bndbox>
	</object>
	<object>
		<name>beaker</name>
		<pose>Unspecified</pose>
		<truncated>0</truncated>
		<difficult>0</difficult>
		<bndbox>
			<xmin>663</xmin>
			<ymin>261</ymin>
			<xmax>799</xmax>
			<ymax>444</ymax>
		</bndbox>
	</object>
	<object>
		<name>narrow-necked-bottle</name>
		<pose>Unspecified</pose>
		<truncated>0</truncated>
		<difficult>0</difficult>
		<bndbox>
			<xmin>980</xmin>
			<ymin>380</ymin>
			<xmax>1127</xmax>
			<ymax>630</ymax>
		</bndbox>
	</object>
	<object>
		<name>hand</name>
		<pose>Unspecified</pose>
		<truncated>0</truncated>
		<difficult>0</difficult>
		<bndbox>
			<xmin>549</xmin>
			<ymin>132</ymin>
			<xmax>738</xmax>
			<ymax>266</ymax>
		</bndbox>
	</object>
	<object>
		<name>hand</name>
		<pose>Unspecified</pose>
		<truncated>0</truncated>
		<difficult>0</difficult>
		<bndbox>
			<xmin>740</xmin>
			<ymin>154</ymin>
			<xmax>913</xmax>
			<ymax>281</ymax>
		</bndbox>
	</object>
</annotation>
