<annotation>
	<folder>图片标注1</folder>
	<filename>004266.jpg</filename>
	<path>D:\桌面\毕设标注\毕设标注1\图片标注1\004266.jpg</path>
	<source>
		<database>Unknown</database>
	</source>
	<size>
		<width>1280</width>
		<height>720</height>
		<depth>3</depth>
	</size>
	<segmented>0</segmented>
	<object>
		<name>narrow-necked-bottle</name>
		<pose>Unspecified</pose>
		<truncated>0</truncated>
		<difficult>0</difficult>
		<bndbox>
			<xmin>85</xmin>
			<ymin>417</ymin>
			<xmax>221</xmax>
			<ymax>656</ymax>
		</bndbox>
	</object>
	<object>
		<name>alcohol-burner</name>
		<pose>Unspecified</pose>
		<truncated>0</truncated>
		<difficult>0</difficult>
		<bndbox>
			<xmin>820</xmin>
			<ymin>374</ymin>
			<xmax>1059</xmax>
			<ymax>632</ymax>
		</bndbox>
	</object>
	<object>
		<name>beaker</name>
		<pose>Unspecified</pose>
		<truncated>0</truncated>
		<difficult>0</difficult>
		<bndbox>
			<xmin>886</xmin>
			<ymin>81</ymin>
			<xmax>1042</xmax>
			<ymax>288</ymax>
		</bndbox>
	</object>
	<object>
		<name>hand</name>
		<pose>Unspecified</pose>
		<truncated>0</truncated>
		<difficult>0</difficult>
		<bndbox>
			<xmin>651</xmin>
			<ymin>380</ymin>
			<xmax>886</xmax>
			<ymax>604</ymax>
		</bndbox>
	</object>
	<object>
		<name>hand</name>
		<pose>Unspecified</pose>
		<truncated>0</truncated>
		<difficult>0</difficult>
		<bndbox>
			<xmin>1001</xmin>
			<ymin>381</ymin>
			<xmax>1157</xmax>
			<ymax>551</ymax>
		</bndbox>
	</object>
	<object>
		<name>asbestos-net</name>
		<pose>Unspecified</pose>
		<truncated>0</truncated>
		<difficult>0</difficult>
		<bndbox>
			<xmin>748</xmin>
			<ymin>253</ymin>
			<xmax>1173</xmax>
			<ymax>299</ymax>
		</bndbox>
	</object>
	<object>
		<name>tripod</name>
		<pose>Unspecified</pose>
		<truncated>0</truncated>
		<difficult>0</difficult>
		<bndbox>
			<xmin>820</xmin>
			<ymin>276</ymin>
			<xmax>1150</xmax>
			<ymax>641</ymax>
		</bndbox>
	</object>
</annotation>
