<annotation>
	<folder>图片标注1</folder>
	<filename>002580.jpg</filename>
	<path>D:\桌面\毕设标注\毕设标注1\图片标注1\002580.jpg</path>
	<source>
		<database>Unknown</database>
	</source>
	<size>
		<width>720</width>
		<height>576</height>
		<depth>3</depth>
	</size>
	<segmented>0</segmented>
	<object>
		<name>narrow-necked-bottle</name>
		<pose>Unspecified</pose>
		<truncated>0</truncated>
		<difficult>0</difficult>
		<bndbox>
			<xmin>123</xmin>
			<ymin>208</ymin>
			<xmax>277</xmax>
			<ymax>501</ymax>
		</bndbox>
	</object>
	<object>
		<name>narrow-necked-bottle</name>
		<pose>Unspecified</pose>
		<truncated>0</truncated>
		<difficult>0</difficult>
		<bndbox>
			<xmin>298</xmin>
			<ymin>259</ymin>
			<xmax>418</xmax>
			<ymax>501</ymax>
		</bndbox>
	</object>
	<object>
		<name>beaker</name>
		<pose>Unspecified</pose>
		<truncated>0</truncated>
		<difficult>0</difficult>
		<bndbox>
			<xmin>471</xmin>
			<ymin>311</ymin>
			<xmax>611</xmax>
			<ymax>506</ymax>
		</bndbox>
	</object>
	<object>
		<name>beaker</name>
		<pose>Unspecified</pose>
		<truncated>0</truncated>
		<difficult>0</difficult>
		<bndbox>
			<xmin>324</xmin>
			<ymin>142</ymin>
			<xmax>395</xmax>
			<ymax>454</ymax>
		</bndbox>
	</object>
</annotation>
